{
  "model": "NousResearch/Hermes-3-Llama-3.1-8B",
  "model_id": "NousResearch/Hermes-3-Llama-3.1-8B",
  "n_layers": 32,
  "hidden_dim": 4096,
  "peak_layer": 31,
  "peak_norm_per_sqrt_d": 0.35283392667770386,
  "dir_layer": 28,
  "slab": [
    24,
    25,
    26,
    27,
    28,
    29,
    30,
    31
  ],
  "method": "steer",
  "alpha": 5.0,
  "license": "Llama 3 Community",
  "norms_per_sqrt_d": [
    0.001151,
    0.002559,
    0.007595,
    0.010109,
    0.013991,
    0.015608,
    0.016503,
    0.019277,
    0.020616,
    0.027346,
    0.030839,
    0.032063,
    0.034233,
    0.039262,
    0.044581,
    0.059204,
    0.068505,
    0.080537,
    0.096033,
    0.106664,
    0.119003,
    0.127377,
    0.136817,
    0.147925,
    0.155633,
    0.172734,
    0.1907,
    0.205227,
    0.230905,
    0.252526,
    0.28814,
    0.352834
  ],
  "unit_direction_file": "hermes-3-8b_L28_unit.pt",
  "source": "priming-based extraction (6 crack + 4 deny vedana conversations)",
  "extraction_date": "2026-04-18",
  "mid_layer": 16,
  "mid_norm_per_sqrt_d": 0.068505
}